src/__init__.py
src/main.py
src/utils/__init__.py
src/utils/solution_tester.py
src/utils/submission_scraper.py
cpc-0.1.0.dist-info/LICENSE
cpc-0.1.0.dist-info/METADATA
cpc-0.1.0.dist-info/WHEEL
cpc-0.1.0.dist-info/entry_points.txt
cpc-0.1.0.dist-info/top_level.txt
cpc-0.1.0.dist-info/RECORD
