Metadata-Version: 2.1
Name: cpc
Version: 0.1.0
Summary: A CLI for competitive programmers
Home-page: https://github.com/purhan/cpc
Author: Purhan Kaushik
Author-email: purhan01@gmail.com
License: UNKNOWN
Platform: UNKNOWN
Classifier: Programming Language :: Python :: 3
Classifier: License :: OSI Approved :: MIT License
Classifier: Operating System :: OS Independent
Requires-Python: >=3.6
Requires-Dist: click (==7.1.2)
Requires-Dist: click-aliases (==1.0.1)
Requires-Dist: termcolor (==1.1.0)
Requires-Dist: requests (==2.25.1)
Requires-Dist: bs4 (==0.0.1)
Requires-Dist: pyyaml (==5.3.1)
Requires-Dist: black (==20.8b1)
